thlock/__init__.py
thlock/etcd_lock.py
thlock/redis_lock.py
thlock-0.9.6.dist-info/LICENSE
thlock-0.9.6.dist-info/METADATA
thlock-0.9.6.dist-info/WHEEL
thlock-0.9.6.dist-info/RECORD
