Metadata-Version: 2.1
Name: thlock
Version: 0.9.6
Summary: TangledHub thlock library
Home-page: https://gitlab.com/tangledlabs/thlock
License: BSD 3-clause
Keywords: tangled,tangledlabs,tangledhub,thlock
Author: TangledHub
Author-email: info@tangledgroup.com
Requires-Python: >=3.10,<4.0
Classifier: Development Status :: 4 - Beta
Classifier: Intended Audience :: Developers
Classifier: License :: OSI Approved :: BSD License
Classifier: License :: Other/Proprietary License
Classifier: Operating System :: OS Independent
Classifier: Programming Language :: Python
Classifier: Programming Language :: Python :: 3
Classifier: Programming Language :: Python :: 3.10
Classifier: Programming Language :: Python :: 3.11
Classifier: Programming Language :: Python :: 3.10
Classifier: Programming Language :: Python :: 3.11
Classifier: Topic :: Software Development :: Libraries :: Python Modules
Requires-Dist: aetcd (>=1.0.0a2,<2.0.0)
Requires-Dist: redis (>=4.4.0,<5.0.0)
Project-URL: Repository, https://gitlab.com/tangledlabs/thlock
